team_former/__init__.py
team_former/make_teams.py
team_former-1.0.1.dist-info/licenses/LICENSE
team_former-1.0.1.dist-info/METADATA
team_former-1.0.1.dist-info/WHEEL
team_former-1.0.1.dist-info/entry_points.txt
team_former-1.0.1.dist-info/top_level.txt
team_former-1.0.1.dist-info/RECORD
