Metadata-Version: 2.4
Name: team_former
Version: 1.0.1
Summary: A team allocation tool using OR-Tools.
Home-page: https://github.com/mgb45/teamformer
Author: Michael Burke
Author-email: michael.g.burke@monash.edu
Classifier: Programming Language :: Python :: 3
Classifier: Operating System :: OS Independent
Requires-Python: >=3.6
License-File: LICENSE
Requires-Dist: pandas
Requires-Dist: ortools
Requires-Dist: fire
Requires-Dist: openpyxl
Requires-Dist: xlrd
Dynamic: author
Dynamic: author-email
Dynamic: classifier
Dynamic: description
Dynamic: description-content-type
Dynamic: home-page
Dynamic: license-file
Dynamic: requires-dist
Dynamic: requires-python
Dynamic: summary
